fast_automl/__init__.py
fast_automl/automl.py
fast_automl/baseline.py
fast_automl/cv_estimators.py
fast_automl/ensemble.py
fast_automl/linear_model.py
fast_automl/metrics.py
fast_automl/test.py
fast_automl/utils.py
fast_automl-0.0.1.dist-info/LICENSE
fast_automl-0.0.1.dist-info/METADATA
fast_automl-0.0.1.dist-info/WHEEL
fast_automl-0.0.1.dist-info/top_level.txt
fast_automl-0.0.1.dist-info/RECORD
