Metadata-Version: 2.1
Name: fast-automl
Version: 0.0.1
Summary: ML for reasonable results in a reasonable amount of time
Home-page: https://dsbowen.github.io/fast-automl
Author: Dillon Bowen
Author-email: dsbowen@wharton.upenn.edu
License: UNKNOWN
Platform: UNKNOWN
Classifier: Programming Language :: Python :: 3
Classifier: License :: OSI Approved :: MIT License
Classifier: Operating System :: OS Independent
Requires-Python: >=3.6
Requires-Dist: joblib (>=0.17.0)
Requires-Dist: numpy (>=1.19.4)
Requires-Dist: pandas (>=1.1.5)
Requires-Dist: scikit-learn (>=0.24.1)
Requires-Dist: scipy (>=1.5.4)
Requires-Dist: xgboost (>=1.3.3)
